mythic_container/AuthBase.py
mythic_container/C2ProfileBase.py
mythic_container/CustomBrowserBase.py
mythic_container/EventingBase.py
mythic_container/LoggingBase.py
mythic_container/MythicCommandBase.py
mythic_container/MythicRPC.py
mythic_container/PayloadBuilder.py
mythic_container/SharedClasses.py
mythic_container/TranslationBase.py
mythic_container/WebhookBase.py
mythic_container/__init__.py
mythic_container/agent_utils.py
mythic_container/auth_utils.py
mythic_container/c2_utils.py
mythic_container/config.py
mythic_container/custombrowser_utils.py
mythic_container/eventing_utils.py
mythic_container/logging.py
mythic_container/logging_utils.py
mythic_container/mythic_service.py
mythic_container/rabbitmq.py
mythic_container/utils_mythic_file_transfer.py
mythic_container/webhook_utils.py
mythic_container/MythicGoRPC/__init__.py
mythic_container/MythicGoRPC/callback_display_to_real_id.py
mythic_container/MythicGoRPC/send_mythic_rpc_agentstorage_create.py
mythic_container/MythicGoRPC/send_mythic_rpc_agentstorage_remove.py
mythic_container/MythicGoRPC/send_mythic_rpc_agentstorage_search.py
mythic_container/MythicGoRPC/send_mythic_rpc_apitoken_create.py
mythic_container/MythicGoRPC/send_mythic_rpc_artifact_create.py
mythic_container/MythicGoRPC/send_mythic_rpc_artifact_search.py
mythic_container/MythicGoRPC/send_mythic_rpc_c2_update_status.py
mythic_container/MythicGoRPC/send_mythic_rpc_callback_add_command.py
mythic_container/MythicGoRPC/send_mythic_rpc_callback_create.py
mythic_container/MythicGoRPC/send_mythic_rpc_callback_decrypt_bytes.py
mythic_container/MythicGoRPC/send_mythic_rpc_callback_display_to_real_id.py
mythic_container/MythicGoRPC/send_mythic_rpc_callback_edge_remove.py
mythic_container/MythicGoRPC/send_mythic_rpc_callback_edge_search.py
mythic_container/MythicGoRPC/send_mythic_rpc_callback_encrypt_bytes.py
mythic_container/MythicGoRPC/send_mythic_rpc_callback_next_checkin_range.py
mythic_container/MythicGoRPC/send_mythic_rpc_callback_remove_command.py
mythic_container-0.6.12.dist-info/licenses/LICENSE.md
mythic_container-0.6.12.dist-info/METADATA
mythic_container-0.6.12.dist-info/WHEEL
mythic_container-0.6.12.dist-info/top_level.txt
mythic_container-0.6.12.dist-info/RECORD
