Metadata-Version: 2.4
Name: mythic_container
Version: 0.6.12
Summary: Functionality for Mythic Services
Home-page: https://docs.mythic-c2.net/customizing/payload-type-development
Author: @its_a_feature_
Author-email: 
License: BSD3
Classifier: License :: Other/Proprietary License
Classifier: Programming Language :: Python :: 3
Classifier: Programming Language :: Python :: 3.11
License-File: LICENSE.md
Requires-Dist: aio_pika==9.4.1
Requires-Dist: dynaconf==3.2.5
Requires-Dist: ujson==5.9.0
Requires-Dist: aiohttp==3.9.3
Requires-Dist: psutil==5.9.8
Requires-Dist: grpcio
Requires-Dist: grpcio-tools
Dynamic: author
Dynamic: classifier
Dynamic: description
Dynamic: description-content-type
Dynamic: home-page
Dynamic: license
Dynamic: license-file
Dynamic: requires-dist
Dynamic: summary
